sqlinjectlib/__init__.py
sqlinjectlib/_blindinject.py
sqlinjectlib/_databases.py
sqlinjectlib/_sqlinjectlib.py
sqlinjectlib/_table.py
sqlinjectlib/_timeinject.py
sqlinjectlib/_typedql.py
sqlinjectlib/_unioninject.py
sqlinjectlib/_utils.py
sqlinjectlib/py.typed
sqlinjectlib-0.1.2.dist-info/LICENSE
sqlinjectlib-0.1.2.dist-info/WHEEL
sqlinjectlib-0.1.2.dist-info/METADATA
sqlinjectlib-0.1.2.dist-info/RECORD
