Metadata-Version: 2.1
Name: sqlinjectlib
Version: 0.1.2
Summary: A library to simplify SQL injections during CTFs
Home-page: https://github.com/rikyiso01/sqlinjectlib
Keywords: sqlinjection
Author: rikyiso01
Author-email: riky.isola@gmail.com
Requires-Python: >=3.10,<4.0
Classifier: Development Status :: 4 - Beta
Classifier: License :: OSI Approved :: GNU General Public License v3 (GPLv3)
Classifier: Operating System :: POSIX :: Linux
Classifier: Programming Language :: Python :: 3
Classifier: Programming Language :: Python :: 3.10
Classifier: Programming Language :: Python :: 3.11
Classifier: Programming Language :: Python :: 3
Classifier: Programming Language :: Python :: 3 :: Only
Classifier: Programming Language :: Python :: 3.10
Classifier: Programming Language :: Python :: 3.11
Classifier: Topic :: Database
Classifier: Topic :: Utilities
Classifier: Typing :: Typed
Requires-Dist: typing-extensions (>=4.4.0,<5.0.0)
Project-URL: Bug Tracker, https://github.com/rikyiso01/sqlinjectlib/issues
Project-URL: Documentation, https://rikyiso01.github.io/sqlinjectlib
Project-URL: Repository, https://github.com/rikyiso01/sqlinjectlib
